setup.py
tgext/__init__.py
tgext.djangoforms.egg-info/PKG-INFO
tgext.djangoforms.egg-info/SOURCES.txt
tgext.djangoforms.egg-info/dependency_links.txt
tgext.djangoforms.egg-info/namespace_packages.txt
tgext.djangoforms.egg-info/requires.txt
tgext.djangoforms.egg-info/top_level.txt
tgext/djangoforms/__init__.py
tgext/djangoforms/constants.py
tgext/djangoforms/lib.py