Metadata-Version: 1.0
Name: tgext.djangoforms
Version: 0.0.1
Summary: Allows you to use django forms with turbogears
Home-page: https://github.com/nickpholden/tgext.djangoforms
Author: Nick Holden
Author-email: nickpholden@gmail.com
License: LGPL
Keywords: turbogears2.extension pylons
Platform: UNKNOWN
Classifier: Environment :: Web Environment
Classifier: Topic :: Software Development :: Libraries :: Python Modules
Classifier: Framework :: TurboGears
